cam_motion_field/__init__.py
cam_motion_field/grid_optical_flow.py
cam_motion_field/optical_flow.py
cam_motion_field-1.4.dist-info/LICENSE
cam_motion_field-1.4.dist-info/METADATA
cam_motion_field-1.4.dist-info/WHEEL
cam_motion_field-1.4.dist-info/top_level.txt
cam_motion_field-1.4.dist-info/RECORD
