Metadata-Version: 2.1
Name: cam-motion-field
Version: 1.4
Summary: This package provides quick and easy way to compute camera motion field given two consecutive images.
Home-page: https://github.com/stamas02/cam_motion_field
Author: Tamas Suveges
Author-email: stamas01@gmail.com
License: MIT
Download-URL: https://github.com/stamas02/cam_motion_field/archive/v_014.tar.gz
Keywords: video,optical-flow,camera,camera-motion,motion field
Platform: UNKNOWN
Classifier: Development Status :: 4 - Beta
Classifier: Intended Audience :: Developers
Classifier: Topic :: Software Development :: Build Tools
Classifier: License :: OSI Approved :: MIT License
Classifier: Programming Language :: Python :: 3
Classifier: Programming Language :: Python :: 3.4
Classifier: Programming Language :: Python :: 3.5
Classifier: Programming Language :: Python :: 3.6
Classifier: Programming Language :: Python :: 3.7
Classifier: Programming Language :: Python :: 3.8
Requires-Dist: opencv-python
Requires-Dist: numpy
